{"assets":{"5A9F7F5C677C799BC23DBA081868E329":{"type":"texture","index":10,"assetRequest":{"type":"slide","state":"outgoing","slide":"53E7848F-1B9C-4C42-8E66-8EA568BCE3E2"},"url":{"web":"assets/5A9F7F5C677C799BC23DBA081868E329.svg"},"width":1024,"height":768},"5CB946EB58E385582FD1A4A130452490":{"type":"texture","index":11,"assetRequest":{"type":"slide","state":"incoming","slide":"7511B892-6589-41F2-B86C-20A6CAB5C41B"},"url":{"web":"assets/5CB946EB58E385582FD1A4A130452490.svg"},"width":1024,"height":768}},"events":[{"effects":[{"beginTime":0,"baseLayer":{"animations":[],"initialState":{"affineTransform":[1,0,0,1,0,0],"masksToBounds":false,"rotation":0,"scale":1,"position":{"pointX":512,"pointY":384},"width":1024,"sublayerTransform":[1,0,0,0,0,1,0,0,0,0,1,0,0,0,0,1],"contentsRect":{"y":0,"x":0,"width":1,"height":1},"opacity":1,"edgeAntialiasingMask":251658240,"height":768,"hidden":false,"anchorPoint":{"pointX":0.5,"pointY":0.5}},"objectID":"0","layers":[{"animations":[],"initialState":{"affineTransform":[1,0,0,1,0,0],"masksToBounds":false,"rotation":0,"scale":1,"position":{"pointX":512,"pointY":384},"width":1024,"sublayerTransform":[1,0,0,0,0,1,0,0,0,0,1,-0.0004922987690640373,0,0,0,1],"contentsRect":{"y":0,"x":0,"width":1,"height":1},"opacity":1,"edgeAntialiasingMask":251658240,"height":768,"hidden":false,"anchorPoint":{"pointX":0.5,"pointY":0.5}},"layers":[{"animations":[],"layers":[],"initialState":{"affineTransform":[1,0,0,1,0,0],"masksToBounds":false,"rotation":0,"scale":1,"position":{"pointX":512,"pointY":384},"width":1024,"sublayerTransform":[1,0,0,0,0,1,0,0,0,0,1,0,0,0,0,1],"contentsRect":{"y":0,"x":0,"width":1,"height":1},"opacity":1,"edgeAntialiasingMask":0,"height":768,"hidden":false,"anchorPoint":{"pointX":0.5,"pointY":0.5}},"texture":"5CB946EB58E385582FD1A4A130452490"},{"animations":[{"timeOffset":0,"from":{"scalar":false},"beginTime":0,"repeatCount":0,"fillMode":"both","property":"hidden","autoreverses":false,"duration":0.01,"to":{"scalar":true}}],"layers":[],"initialState":{"affineTransform":[1,0,0,1,0,0],"masksToBounds":false,"rotation":0,"scale":1,"position":{"pointX":512,"pointY":384},"width":1024,"sublayerTransform":[1,0,0,0,0,1,0,0,0,0,1,0,0,0,0,1],"contentsRect":{"y":0,"x":0,"width":1,"height":1},"opacity":1,"edgeAntialiasingMask":0,"height":768,"hidden":false,"anchorPoint":{"pointX":0.5,"pointY":0.5}},"texture":"5A9F7F5C677C799BC23DBA081868E329"}]}]},"effects":[],"duration":0.01,"type":"transition","name":"none","objectID":"0"}],"automaticPlay":false,"hyperlinks":[],"accessibility":[{"text":"62fcc19","targetRectangle":{"y":290.9956059455872,"x":805.547527551651,"width":54.21000000000004,"height":18}},{"text":"id1","targetRectangle":{"y":172.5214841365814,"x":685.356841802597,"width":33.33600000000001,"height":29}},{"text":"{name: “Atul”, age: 45}","targetRectangle":{"y":305.3662109375,"x":826.336013671875,"width":154.7280000000001,"height":58}},{"text":"table","targetRectangle":{"y":171,"x":299.3272653808594,"width":53.35199999999998,"height":29}},{"text":"id2","targetRectangle":{"y":255.2728879451752,"x":685.7464292049408,"width":33.33600000000001,"height":29}},{"text":"table","targetRectangle":{"y":171,"x":531.2276865234375,"width":53.35200000000009,"height":29}},{"text":"{name: “Ella”, age: 36}","targetRectangle":{"y":455.3662109375,"x":827.680013671875,"width":152.04,"height":58}},{"text":"id3","targetRectangle":{"y":329.188140630722,"x":686.356841802597,"width":33.33600000000001,"height":29}},{"text":"People","targetRectangle":{"y":446.7844541072845,"x":72.65031433105469,"width":86.4140625,"height":29}},{"text":"second commit","targetRectangle":{"y":171,"x":46.74093380737305,"width":165.384,"height":29}},{"text":"(SSTable, CSV, JSON, SQLite, etc)","targetRectangle":{"y":93.52415442466736,"x":328.1719961166382,"width":367.6560000000001,"height":29}},{"text":"{name: “Maria”, age: 24}","targetRectangle":{"y":160.6995697021484,"x":817.012013671875,"width":173.376,"height":58}},{"text":"people","targetRectangle":{"y":170.5214841365814,"x":402.1559985876083,"width":74.68799999999999,"height":29}},{"text":"0aa0d2","targetRectangle":{"y":145.5094609260559,"x":807.220027923584,"width":50.86500000000001,"height":18}},{"text":"export to","targetRectangle":{"y":312.3161015510559,"x":324.1479992866516,"width":142.704,"height":43}},{"text":"Export to Data Formats instead of a Working Tree","targetRectangle":{"y":44.34956407546997,"x":89.23731231689453,"width":845.525390625,"height":43}},{"text":"6ff3c75","targetRectangle":{"y":440.9956059455872,"x":807.7675263881683,"width":49.76999999999998,"height":18}}],"baseLayer":{"animations":[],"initialState":{"affineTransform":[1,0,0,1,0,0],"masksToBounds":false,"rotation":0,"scale":1,"position":{"pointX":512,"pointY":384},"width":1024,"sublayerTransform":[1,0,0,0,0,1,0,0,0,0,1,0,0,0,0,1],"contentsRect":{"y":0,"x":0,"width":1,"height":1},"opacity":1,"edgeAntialiasingMask":251658240,"height":768,"hidden":false,"anchorPoint":{"pointX":0.5,"pointY":0.5}},"objectID":"0","layers":[{"animations":[],"initialState":{"affineTransform":[1,0,0,1,0,0],"masksToBounds":false,"rotation":0,"scale":1,"position":{"pointX":512,"pointY":384},"width":1024,"sublayerTransform":[1,0,0,0,0,1,0,0,0,0,1,-0.0004922987690640373,0,0,0,1],"contentsRect":{"y":0,"x":0,"width":1,"height":1},"opacity":1,"edgeAntialiasingMask":251658240,"height":768,"hidden":false,"anchorPoint":{"pointX":0.5,"pointY":0.5}},"layers":[{"animations":[],"layers":[],"initialState":{"affineTransform":[1,0,0,1,0,0],"masksToBounds":false,"rotation":0,"scale":1,"position":{"pointX":512,"pointY":384},"width":1024,"sublayerTransform":[1,0,0,0,0,1,0,0,0,0,1,0,0,0,0,1],"contentsRect":{"y":0,"x":0,"width":1,"height":1},"opacity":1,"edgeAntialiasingMask":0,"height":768,"hidden":false,"anchorPoint":{"pointX":0.5,"pointY":0.5}},"texture":"5A9F7F5C677C799BC23DBA081868E329"}]}]}}]}